{
  "dictionaries": [],
  "dictionaryDefinitions": [],
  "ignorePaths": [],
  "ignoreWords": [
    "depcruiser",
    "depcruiserrc",
    "ehildt",
    "litlbyte"
  ],
  "import": [],
  "version": "0.2",
  "words": [
    "backmerge",
    "cobertura",
    "commitlint",
    "conventionalcommits",
    "corpintra",
    "cultify",
    "depcruise",
    "dtos",
    "Eugen",
    "Fastify",
    "gitleaks",
    "Hildt",
    "INITDB",
    "loglevel",
    "logpath",
    "microservices",
    "mongod",
    "ndjson",
    "nestjs",
    "reqs",
    "saithodev",
    "sonarjs",
    "Streamable",
    "styl",
    "Upserts",
    "zricethezav"
  ]
}